MaCroDNA/__init__.py
MaCroDNA/macrodna.py
MaCroDNA-0.0.1.dist-info/LICENSE
MaCroDNA-0.0.1.dist-info/METADATA
MaCroDNA-0.0.1.dist-info/WHEEL
MaCroDNA-0.0.1.dist-info/top_level.txt
MaCroDNA-0.0.1.dist-info/RECORD
