Metadata-Version: 2.1
Name: MaCroDNA
Version: 0.0.1
Summary: Accurate integration of single-cell DNA and RNA data for a deeper understanding of tumor heterogeneity
Home-page: https://github.com/xiru-huang/MaCroDNA
Author: Mohammadamin Edrisi, Xiru Huang
Author-email: mae6@rice.edu, xh29@rice.edu
Project-URL: Bug Tracker, https://github.com/xiru-huang/MaCroDNA/issues
Classifier: Programming Language :: Python :: 3
Classifier: License :: OSI Approved :: MIT License
Classifier: Operating System :: OS Independent
Requires-Python: >=3.7
License-File: LICENSE
Requires-Dist: numpy
Requires-Dist: pandas
Requires-Dist: scipy
